{
  "id": "设计与实现/Pika 源码学习笔记/Pika 和 RockSDB 的对接/index",
  "title": "Pika 和 RockSDB 的对接",
  "description": "在《Pika源码学习--pika的命令执行框架》中我们了解了一个命令的执行流程，也知道了pika使用的是Blackwidow引擎，现在我们来看看pika是怎么和rocksdb对接的，Blackwidow具体怎么处理命令。",
  "source": "@site/docs/设计与实现/Pika 源码学习笔记/Pika 和 RockSDB 的对接/index.md",
  "sourceDirName": "设计与实现/Pika 源码学习笔记/Pika 和 RockSDB 的对接",
  "slug": "/设计与实现/Pika 源码学习笔记/Pika 和 RockSDB 的对接/",
  "permalink": "/docs/设计与实现/Pika 源码学习笔记/Pika 和 RockSDB 的对接/",
  "draft": false,
  "unlisted": false,
  "editUrl": "https://atomgit.com/zouxiangneihe/website/tree/master/docs/设计与实现/Pika 源码学习笔记/Pika 和 RockSDB 的对接/index.md",
  "tags": [],
  "version": "current",
  "sidebarPosition": 3,
  "frontMatter": {
    "title": "Pika 和 RockSDB 的对接",
    "sidebar_position": 3
  },
  "sidebar": "tutorialSidebar",
  "previous": {
    "title": "Pika 的命令执行框架",
    "permalink": "/docs/设计与实现/Pika 源码学习笔记/Pika 的命令执行框架/"
  },
  "next": {
    "title": "Pika 传火计划",
    "permalink": "/docs/设计与实现/Pika 传火计划/"
  }
}