{
  "id": "设计与实现/整体技术架构/index",
  "title": "整体技术架构",
  "description": "概述",
  "source": "@site/docs/设计与实现/整体技术架构/index.md",
  "sourceDirName": "设计与实现/整体技术架构",
  "slug": "/设计与实现/整体技术架构/",
  "permalink": "/docs/设计与实现/整体技术架构/",
  "draft": false,
  "unlisted": false,
  "editUrl": "https://atomgit.com/zouxiangneihe/website/tree/master/docs/设计与实现/整体技术架构/index.md",
  "tags": [],
  "version": "current",
  "sidebarPosition": 0,
  "frontMatter": {
    "title": "整体技术架构",
    "sidebar_position": 0
  },
  "sidebar": "tutorialSidebar",
  "previous": {
    "title": "设计与实现",
    "permalink": "/docs/设计与实现/"
  },
  "next": {
    "title": "线程模型",
    "permalink": "/docs/设计与实现/线程模型/"
  }
}