{
  "id": "设计与实现/Pika 传火计划/index",
  "title": "Pika 传火计划",
  "description": "为方便刚接触Pika的同学能够更快的上手提交第一个Pika PR。基于v3.3.4代码，从代码层面对Pika进行了全方面的梳理。这个想法叫传火计划，希望Pika星星之火可以燎原。",
  "source": "@site/docs/设计与实现/Pika 传火计划/index.md",
  "sourceDirName": "设计与实现/Pika 传火计划",
  "slug": "/设计与实现/Pika 传火计划/",
  "permalink": "/docs/设计与实现/Pika 传火计划/",
  "draft": false,
  "unlisted": false,
  "editUrl": "https://atomgit.com/zouxiangneihe/website/tree/master/docs/设计与实现/Pika 传火计划/index.md",
  "tags": [],
  "version": "current",
  "sidebarPosition": 18,
  "frontMatter": {
    "title": "Pika 传火计划",
    "sidebar_position": 18
  },
  "sidebar": "tutorialSidebar",
  "previous": {
    "title": "Pika 和 RockSDB 的对接",
    "permalink": "/docs/设计与实现/Pika 源码学习笔记/Pika 和 RockSDB 的对接/"
  },
  "next": {
    "title": "Pika 线程模型简介",
    "permalink": "/docs/设计与实现/Pika 传火计划/线程模型/"
  }
}